{
    "blockly": false,
    "blockly_xml": "<xml></xml>",
    "category": "Uncategorized",
    "coa": {
        "data": {
            "description": "",
            "edges": [
                {
                    "id": "port_2_to_port_3",
                    "sourceNode": "2",
                    "sourcePort": "2_out",
                    "targetNode": "3",
                    "targetPort": "3_in"
                },
                {
                    "id": "port_8_to_port_9",
                    "sourceNode": "8",
                    "sourcePort": "8_out",
                    "targetNode": "9",
                    "targetPort": "9_in"
                },
                {
                    "id": "port_8_to_port_10",
                    "sourceNode": "8",
                    "sourcePort": "8_out",
                    "targetNode": "10",
                    "targetPort": "10_in"
                },
                {
                    "conditions": [
                        {
                            "conditionKey": "condition_key_0",
                            "index": 0
                        }
                    ],
                    "id": "port_9_to_port_6",
                    "sourceNode": "9",
                    "sourcePort": "9_out",
                    "targetNode": "6",
                    "targetPort": "6_in"
                },
                {
                    "conditions": [
                        {
                            "conditionKey": "condition_key_12",
                            "index": 1
                        }
                    ],
                    "id": "port_4_to_port_5",
                    "sourceNode": "4",
                    "sourcePort": "4_out",
                    "targetNode": "5",
                    "targetPort": "5_in"
                },
                {
                    "id": "port_0_to_port_12",
                    "sourceNode": "0",
                    "sourcePort": "0_out",
                    "targetNode": "12",
                    "targetPort": "12_in"
                },
                {
                    "id": "port_12_to_port_2",
                    "sourceNode": "12",
                    "sourcePort": "12_out",
                    "targetNode": "2",
                    "targetPort": "2_in"
                },
                {
                    "id": "port_2_to_port_13",
                    "sourceNode": "2",
                    "sourcePort": "2_out",
                    "targetNode": "13",
                    "targetPort": "13_in"
                },
                {
                    "conditions": [
                        {
                            "conditionKey": "condition_key_0",
                            "index": 0
                        }
                    ],
                    "id": "port_13_to_port_4",
                    "sourceNode": "13",
                    "sourcePort": "13_out",
                    "targetNode": "4",
                    "targetPort": "4_in"
                },
                {
                    "id": "port_8_to_port_14",
                    "sourceNode": "8",
                    "sourcePort": "8_out",
                    "targetNode": "14",
                    "targetPort": "14_in"
                },
                {
                    "conditions": [
                        {
                            "conditionKey": "condition_key_0",
                            "index": 0
                        }
                    ],
                    "id": "port_4_to_port_15",
                    "sourceNode": "4",
                    "sourcePort": "4_out",
                    "targetNode": "15",
                    "targetPort": "15_in"
                },
                {
                    "id": "port_15_to_port_8",
                    "sourceNode": "15",
                    "sourcePort": "15_out",
                    "targetNode": "8",
                    "targetPort": "8_in"
                }
            ],
            "hash": "af686693343936a2ff36931f53b92249c484a405",
            "nodes": {
                "0": {
                    "data": {
                        "advanced": {
                            "join": []
                        },
                        "functionName": "on_start",
                        "id": "0",
                        "type": "start"
                    },
                    "errors": {},
                    "id": "0",
                    "type": "start",
                    "warnings": {},
                    "x": 1000,
                    "y": 220
                },
                "1": {
                    "data": {
                        "advanced": {
                            "join": []
                        },
                        "functionName": "on_finish",
                        "id": "1",
                        "type": "end"
                    },
                    "errors": {},
                    "id": "1",
                    "type": "end",
                    "warnings": {},
                    "x": 960,
                    "y": 1300
                },
                "10": {
                    "data": {
                        "advanced": {
                            "customName": "Debug Prompt response",
                            "customNameId": 0,
                            "join": []
                        },
                        "customDatapaths": {
                            "artifacts": {
                                "artifact:*.cef.act.someother": {
                                    "contains": [],
                                    "isCustomDatapath": true,
                                    "key": "artifact",
                                    "label": "artifact:*.cef.act.someother",
                                    "value": "artifact:*.cef.act.someother"
                                }
                            }
                        },
                        "customFunction": {
                            "draftMode": false,
                            "name": "debug",
                            "repoName": "community"
                        },
                        "functionId": 4,
                        "functionName": "debug_prompt_response",
                        "id": "10",
                        "loop": {
                            "enabled": false,
                            "exitAfterUnit": "m",
                            "exitAfterValue": 10,
                            "exitConditionEnabled": false,
                            "exitLoopAfter": 2,
                            "pauseUnit": "m",
                            "pauseValue": 2
                        },
                        "selectMore": false,
                        "type": "utility",
                        "utilities": {
                            "debug": {
                                "description": "Print debug messages with the type and value of 0-10 different inputs. This is useful for checking the values of input data or the outputs of other playbook blocks.",
                                "fields": [
                                    {
                                        "dataTypes": [
                                            "*"
                                        ],
                                        "description": "",
                                        "inputType": "list",
                                        "label": "input_1",
                                        "name": "input_1",
                                        "placeholder": "",
                                        "renderType": "datapath",
                                        "required": false
                                    },
                                    {
                                        "dataTypes": [
                                            "*"
                                        ],
                                        "description": "",
                                        "inputType": "list",
                                        "label": "input_2",
                                        "name": "input_2",
                                        "placeholder": "",
                                        "renderType": "datapath",
                                        "required": false
                                    },
                                    {
                                        "dataTypes": [
                                            "*"
                                        ],
                                        "description": "",
                                        "inputType": "list",
                                        "label": "input_3",
                                        "name": "input_3",
                                        "placeholder": "",
                                        "renderType": "datapath",
                                        "required": false
                                    },
                                    {
                                        "dataTypes": [
                                            "*"
                                        ],
                                        "description": "",
                                        "inputType": "list",
                                        "label": "input_4",
                                        "name": "input_4",
                                        "placeholder": "",
                                        "renderType": "datapath",
                                        "required": false
                                    },
                                    {
                                        "dataTypes": [
                                            "*"
                                        ],
                                        "description": "",
                                        "inputType": "list",
                                        "label": "input_5",
                                        "name": "input_5",
                                        "placeholder": "",
                                        "renderType": "datapath",
                                        "required": false
                                    },
                                    {
                                        "dataTypes": [
                                            "*"
                                        ],
                                        "description": "",
                                        "inputType": "list",
                                        "label": "input_6",
                                        "name": "input_6",
                                        "placeholder": "",
                                        "renderType": "datapath",
                                        "required": false
                                    },
                                    {
                                        "dataTypes": [
                                            "*"
                                        ],
                                        "description": "",
                                        "inputType": "list",
                                        "label": "input_7",
                                        "name": "input_7",
                                        "placeholder": "",
                                        "renderType": "datapath",
                                        "required": false
                                    },
                                    {
                                        "dataTypes": [
                                            "*"
                                        ],
                                        "description": "",
                                        "inputType": "list",
                                        "label": "input_8",
                                        "name": "input_8",
                                        "placeholder": "",
                                        "renderType": "datapath",
                                        "required": false
                                    },
                                    {
                                        "dataTypes": [
                                            "*"
                                        ],
                                        "description": "",
                                        "inputType": "list",
                                        "label": "input_9",
                                        "name": "input_9",
                                        "placeholder": "",
                                        "renderType": "datapath",
                                        "required": false
                                    },
                                    {
                                        "dataTypes": [
                                            "*"
                                        ],
                                        "description": "",
                                        "inputType": "list",
                                        "label": "input_10",
                                        "name": "input_10",
                                        "placeholder": "",
                                        "renderType": "datapath",
                                        "required": false
                                    }
                                ],
                                "label": "debug",
                                "name": "debug"
                            }
                        },
                        "utilityType": "custom_function",
                        "values": {
                            "debug": {
                                "input_1": [
                                    "prompt_1:action_result.status"
                                ],
                                "input_10": null,
                                "input_2": [
                                    "prompt_1:action_result.summary.responses.0"
                                ],
                                "input_3": [
                                    "Users are slow"
                                ],
                                "input_4": [
                                    "artifact:*.cef.act.someother"
                                ],
                                "input_5": [
                                    "geolocate_ip_1:action_result.data"
                                ],
                                "input_6": null,
                                "input_7": null,
                                "input_8": null,
                                "input_9": null
                            },
                            "set_severity": {
                                "_internal": [
                                    "container"
                                ],
                                "severity": "high"
                            }
                        }
                    },
                    "errors": {},
                    "id": "10",
                    "type": "utility",
                    "warnings": {},
                    "x": 1460,
                    "y": 1044.5
                },
                "11": {
                    "data": {
                        "action": "lookup domain",
                        "actionType": "investigate",
                        "advanced": {
                            "join": []
                        },
                        "connector": "DNS",
                        "connectorConfigs": [
                            "google_dns"
                        ],
                        "connectorId": "876ab991-313e-48e7-bccd-e8c9650c239c",
                        "connectorVersion": "v1",
                        "functionId": 1,
                        "functionName": "lookup_domain_1",
                        "id": "11",
                        "loop": {
                            "enabled": false,
                            "exitAfterUnit": "m",
                            "exitAfterValue": 10,
                            "exitConditionEnabled": false,
                            "exitLoopAfter": 2,
                            "pauseUnit": "m",
                            "pauseValue": 2
                        },
                        "parameters": {},
                        "requiredParameters": [
                            {
                                "data_type": "string",
                                "field": "domain"
                            }
                        ],
                        "type": "action"
                    },
                    "errors": {},
                    "id": "11",
                    "type": "action",
                    "warnings": {
                        "context": [
                            "Connect block to playbook flow."
                        ]
                    },
                    "x": 773.7500610351562,
                    "y": 1137.8751220703125
                },
                "12": {
                    "data": {
                        "advanced": {
                            "join": []
                        },
                        "customFunction": {
                            "draftMode": false,
                            "name": "list_merge",
                            "repoName": "community"
                        },
                        "functionId": 6,
                        "functionName": "list_merge_6",
                        "id": "12",
                        "loop": {
                            "enabled": false,
                            "exitAfterUnit": "m",
                            "exitAfterValue": 10,
                            "exitConditionEnabled": false,
                            "exitLoopAfter": 2,
                            "pauseUnit": "m",
                            "pauseValue": 2
                        },
                        "selectMore": false,
                        "type": "utility",
                        "utilities": {
                            "list_merge": {
                                "description": "Merge 2-10 different data paths into a single output data path. For example, if IP addresses are stored in the fields sourceAddress, destinationAddress, and deviceAddress, then those three fields could be merged together to form a single list of IP addresses.",
                                "fields": [
                                    {
                                        "dataTypes": [
                                            "*"
                                        ],
                                        "description": "",
                                        "inputType": "list",
                                        "label": "input_1",
                                        "name": "input_1",
                                        "placeholder": "",
                                        "renderType": "datapath",
                                        "required": false
                                    },
                                    {
                                        "dataTypes": [
                                            "*"
                                        ],
                                        "description": "",
                                        "inputType": "list",
                                        "label": "input_2",
                                        "name": "input_2",
                                        "placeholder": "",
                                        "renderType": "datapath",
                                        "required": false
                                    },
                                    {
                                        "dataTypes": [
                                            "*"
                                        ],
                                        "description": "",
                                        "inputType": "list",
                                        "label": "input_3",
                                        "name": "input_3",
                                        "placeholder": "",
                                        "renderType": "datapath",
                                        "required": false
                                    },
                                    {
                                        "dataTypes": [
                                            "*"
                                        ],
                                        "description": "",
                                        "inputType": "list",
                                        "label": "input_4",
                                        "name": "input_4",
                                        "placeholder": "",
                                        "renderType": "datapath",
                                        "required": false
                                    },
                                    {
                                        "dataTypes": [
                                            "*"
                                        ],
                                        "description": "",
                                        "inputType": "list",
                                        "label": "input_5",
                                        "name": "input_5",
                                        "placeholder": "",
                                        "renderType": "datapath",
                                        "required": false
                                    },
                                    {
                                        "dataTypes": [
                                            "*"
                                        ],
                                        "description": "",
                                        "inputType": "list",
                                        "label": "input_6",
                                        "name": "input_6",
                                        "placeholder": "",
                                        "renderType": "datapath",
                                        "required": false
                                    },
                                    {
                                        "dataTypes": [
                                            "*"
                                        ],
                                        "description": "",
                                        "inputType": "list",
                                        "label": "input_7",
                                        "name": "input_7",
                                        "placeholder": "",
                                        "renderType": "datapath",
                                        "required": false
                                    },
                                    {
                                        "dataTypes": [
                                            "*"
                                        ],
                                        "description": "",
                                        "inputType": "list",
                                        "label": "input_8",
                                        "name": "input_8",
                                        "placeholder": "",
                                        "renderType": "datapath",
                                        "required": false
                                    },
                                    {
                                        "dataTypes": [
                                            "*"
                                        ],
                                        "description": "",
                                        "inputType": "list",
                                        "label": "input_9",
                                        "name": "input_9",
                                        "placeholder": "",
                                        "renderType": "datapath",
                                        "required": false
                                    },
                                    {
                                        "dataTypes": [
                                            "*"
                                        ],
                                        "description": "",
                                        "inputType": "list",
                                        "label": "input_10",
                                        "name": "input_10",
                                        "placeholder": "",
                                        "renderType": "datapath",
                                        "required": false
                                    }
                                ],
                                "label": "list_merge",
                                "name": "list_merge"
                            }
                        },
                        "utilityType": "custom_function",
                        "values": {
                            "list_merge": {
                                "input_1": [
                                    "artifact:*.cef.destinationAddress"
                                ],
                                "input_10": null,
                                "input_2": [
                                    "artifact:*.cef.deviceAddress"
                                ],
                                "input_3": [
                                    "artifact:*.cef.sourceAddress"
                                ],
                                "input_4": null,
                                "input_5": null,
                                "input_6": null,
                                "input_7": null,
                                "input_8": null,
                                "input_9": null
                            }
                        }
                    },
                    "errors": {},
                    "id": "12",
                    "type": "utility",
                    "warnings": {},
                    "x": 980,
                    "y": 364.4999999999999
                },
                "13": {
                    "data": {
                        "advanced": {
                            "join": []
                        },
                        "conditions": [
                            {
                                "comparisons": [
                                    {
                                        "conditionIndex": 0,
                                        "op": "!=",
                                        "param": "geolocate_ip_1:action_result.data.*.country_iso_code",
                                        "value": "None"
                                    }
                                ],
                                "conditionIndex": 0,
                                "conditionKey": "condition_key_0",
                                "logic": "and"
                            }
                        ],
                        "functionId": 1,
                        "functionName": "filter_1",
                        "id": "13",
                        "type": "filter"
                    },
                    "errors": {},
                    "id": "13",
                    "type": "filter",
                    "warnings": {},
                    "x": 1040,
                    "y": 580
                },
                "14": {
                    "data": {
                        "advanced": {
                            "join": []
                        },
                        "functionId": 7,
                        "functionName": "add_comment_7",
                        "id": "14",
                        "loop": {
                            "enabled": false,
                            "exitAfterUnit": "m",
                            "exitAfterValue": 10,
                            "exitConditionEnabled": false,
                            "exitLoopAfter": 2,
                            "pauseUnit": "m",
                            "pauseValue": 2
                        },
                        "selectMore": false,
                        "tab": "apis",
                        "type": "utility",
                        "utilities": {
                            "comment": {
                                "description": "",
                                "fields": [
                                    {
                                        "description": "",
                                        "label": "comment",
                                        "name": "comment",
                                        "placeholder": "Enter a comment",
                                        "renderType": "datapath",
                                        "required": true
                                    },
                                    {
                                        "hidden": true,
                                        "name": "container",
                                        "required": false
                                    },
                                    {
                                        "hidden": true,
                                        "name": "author",
                                        "required": false
                                    },
                                    {
                                        "hidden": true,
                                        "name": "trace",
                                        "required": false
                                    }
                                ],
                                "label": "add comment",
                                "name": "comment"
                            }
                        },
                        "utilityType": "api",
                        "values": {
                            "comment": {
                                "_internal": [
                                    "container",
                                    "author",
                                    "trace"
                                ],
                                "comment": "prompt_1:action_result.parameter.message"
                            }
                        }
                    },
                    "errors": {},
                    "id": "14",
                    "type": "utility",
                    "warnings": {},
                    "x": 1060,
                    "y": 1180
                },
                "15": {
                    "data": {
                        "advanced": {
                            "join": []
                        },
                        "functionId": 2,
                        "functionName": "format_2",
                        "id": "15",
                        "parameters": [
                            "filtered-data:filter_1:condition_1:geolocate_ip_1:action_result.parameter.ip",
                            "filtered-data:filter_1:condition_1:geolocate_ip_1:action_result.data.*.country_name",
                            "filtered-data:filter_1:condition_1:geolocate_ip_1:action_result.data.*.country_iso_code"
                        ],
                        "template": "%%\nIP: {0} is from: {1} (ISO Code: {2})\n%%",
                        "type": "format"
                    },
                    "errors": {},
                    "id": "15",
                    "type": "format",
                    "warnings": {},
                    "x": 1260,
                    "y": 740
                },
                "2": {
                    "data": {
                        "action": "geolocate ip",
                        "actionType": "investigate",
                        "advanced": {
                            "join": []
                        },
                        "connector": "MaxMind",
                        "connectorConfigs": [
                            "maxmind"
                        ],
                        "connectorId": "c566e153-3118-4033-abda-14dd9748c91a",
                        "connectorVersion": "v1",
                        "functionId": 1,
                        "functionName": "geolocate_ip_1",
                        "id": "2",
                        "loop": {
                            "enabled": false,
                            "exitAfterUnit": "m",
                            "exitAfterValue": 10,
                            "exitConditionEnabled": false,
                            "exitLoopAfter": 2,
                            "pauseUnit": "m",
                            "pauseValue": 2
                        },
                        "parameters": {
                            "ip": "list_merge_6:custom_function_result.data.item"
                        },
                        "requiredParameters": [
                            {
                                "data_type": "string",
                                "field": "ip"
                            }
                        ],
                        "type": "action"
                    },
                    "errors": {},
                    "id": "2",
                    "type": "action",
                    "warnings": {},
                    "x": 980,
                    "y": 460
                },
                "3": {
                    "data": {
                        "advanced": {
                            "join": []
                        },
                        "customFunction": {
                            "draftMode": false,
                            "name": "debug",
                            "repoName": "community"
                        },
                        "functionId": 1,
                        "functionName": "debug_1",
                        "id": "3",
                        "loop": {
                            "enabled": false,
                            "exitAfterUnit": "m",
                            "exitAfterValue": 10,
                            "exitConditionEnabled": false,
                            "exitLoopAfter": 2,
                            "pauseUnit": "m",
                            "pauseValue": 2
                        },
                        "selectMore": false,
                        "tab": "customFunctions",
                        "type": "utility",
                        "utilities": {
                            "debug": {
                                "description": "Print debug messages with the type and value of 0-10 different inputs. This is useful for checking the values of input data or the outputs of other playbook blocks.",
                                "fields": [
                                    {
                                        "dataTypes": [
                                            "*"
                                        ],
                                        "description": "",
                                        "inputType": "list",
                                        "label": "input_1",
                                        "name": "input_1",
                                        "placeholder": "",
                                        "renderType": "datapath",
                                        "required": false
                                    },
                                    {
                                        "dataTypes": [
                                            "*"
                                        ],
                                        "description": "",
                                        "inputType": "list",
                                        "label": "input_2",
                                        "name": "input_2",
                                        "placeholder": "",
                                        "renderType": "datapath",
                                        "required": false
                                    },
                                    {
                                        "dataTypes": [
                                            "*"
                                        ],
                                        "description": "",
                                        "inputType": "list",
                                        "label": "input_3",
                                        "name": "input_3",
                                        "placeholder": "",
                                        "renderType": "datapath",
                                        "required": false
                                    },
                                    {
                                        "dataTypes": [
                                            "*"
                                        ],
                                        "description": "",
                                        "inputType": "list",
                                        "label": "input_4",
                                        "name": "input_4",
                                        "placeholder": "",
                                        "renderType": "datapath",
                                        "required": false
                                    },
                                    {
                                        "dataTypes": [
                                            "*"
                                        ],
                                        "description": "",
                                        "inputType": "list",
                                        "label": "input_5",
                                        "name": "input_5",
                                        "placeholder": "",
                                        "renderType": "datapath",
                                        "required": false
                                    },
                                    {
                                        "dataTypes": [
                                            "*"
                                        ],
                                        "description": "",
                                        "inputType": "list",
                                        "label": "input_6",
                                        "name": "input_6",
                                        "placeholder": "",
                                        "renderType": "datapath",
                                        "required": false
                                    },
                                    {
                                        "dataTypes": [
                                            "*"
                                        ],
                                        "description": "",
                                        "inputType": "list",
                                        "label": "input_7",
                                        "name": "input_7",
                                        "placeholder": "",
                                        "renderType": "datapath",
                                        "required": false
                                    },
                                    {
                                        "dataTypes": [
                                            "*"
                                        ],
                                        "description": "",
                                        "inputType": "list",
                                        "label": "input_8",
                                        "name": "input_8",
                                        "placeholder": "",
                                        "renderType": "datapath",
                                        "required": false
                                    },
                                    {
                                        "dataTypes": [
                                            "*"
                                        ],
                                        "description": "",
                                        "inputType": "list",
                                        "label": "input_9",
                                        "name": "input_9",
                                        "placeholder": "",
                                        "renderType": "datapath",
                                        "required": false
                                    },
                                    {
                                        "dataTypes": [
                                            "*"
                                        ],
                                        "description": "",
                                        "inputType": "list",
                                        "label": "input_10",
                                        "name": "input_10",
                                        "placeholder": "",
                                        "renderType": "datapath",
                                        "required": false
                                    }
                                ],
                                "label": "debug",
                                "name": "debug"
                            }
                        },
                        "utilityType": "custom_function",
                        "values": {
                            "debug": {
                                "input_1": [
                                    "geolocate_ip_1:action_result.status"
                                ],
                                "input_10": null,
                                "input_2": [
                                    "geolocate_ip_1:action_result.data.*.country_iso_code"
                                ],
                                "input_3": [
                                    "geolocate_ip_1:action_result.data.*.country_name"
                                ],
                                "input_4": [
                                    "container:name"
                                ],
                                "input_5": [
                                    "container:label"
                                ],
                                "input_6": null,
                                "input_7": null,
                                "input_8": null,
                                "input_9": null
                            }
                        }
                    },
                    "errors": {},
                    "id": "3",
                    "type": "utility",
                    "warnings": {},
                    "x": 1320,
                    "y": 580
                },
                "4": {
                    "data": {
                        "advanced": {
                            "customName": "Decide if IPs are in our list",
                            "customNameId": 0,
                            "join": []
                        },
                        "conditions": [
                            {
                                "comparisons": [
                                    {
                                        "conditionIndex": 0,
                                        "op": "!=",
                                        "param": "filtered-data:filter_1:condition_1:geolocate_ip_1:action_result.data.*.country_iso_code",
                                        "value": "US"
                                    },
                                    {
                                        "conditionIndex": 0,
                                        "op": "!=",
                                        "param": "filtered-data:filter_1:condition_1:geolocate_ip_1:action_result.data.*.country_iso_code",
                                        "value": "SA"
                                    },
                                    {
                                        "conditionIndex": 0,
                                        "op": "!=",
                                        "param": "filtered-data:filter_1:condition_1:geolocate_ip_1:action_result.data.*.country_iso_code",
                                        "value": "CA"
                                    }
                                ],
                                "conditionIndex": 0,
                                "conditionKey": "condition_key_0",
                                "customName": "IP is NOT in our list",
                                "display": "If",
                                "logic": "and",
                                "type": "if"
                            },
                            {
                                "comparisons": [
                                    {
                                        "conditionIndex": 1,
                                        "op": "==",
                                        "param": "",
                                        "value": ""
                                    }
                                ],
                                "conditionIndex": 1,
                                "conditionKey": "condition_key_12",
                                "customName": "IP is in our list",
                                "display": "Else",
                                "logic": "and",
                                "type": "else"
                            }
                        ],
                        "functionId": 2,
                        "functionName": "decide_if_ips_are_in_our_list",
                        "id": "4",
                        "type": "decision"
                    },
                    "errors": {},
                    "id": "4",
                    "type": "decision",
                    "warnings": {},
                    "x": 1060,
                    "y": 720
                },
                "5": {
                    "data": {
                        "advanced": {
                            "customName": "set low severity",
                            "customNameId": 0,
                            "join": [],
                            "refreshNotableData": true
                        },
                        "functionId": 2,
                        "functionName": "set_low_severity",
                        "id": "5",
                        "loop": {
                            "enabled": false,
                            "exitAfterUnit": "m",
                            "exitAfterValue": 10,
                            "exitConditionEnabled": false,
                            "exitLoopAfter": 2,
                            "pauseUnit": "m",
                            "pauseValue": 2
                        },
                        "selectMore": false,
                        "tab": "apis",
                        "type": "utility",
                        "utilities": {
                            "set_severity": {
                                "description": "",
                                "fields": [
                                    {
                                        "choices": "notableSeverity",
                                        "description": "",
                                        "label": "severity",
                                        "name": "severity",
                                        "placeholder": "Select severity",
                                        "renderType": "dropdown",
                                        "required": true
                                    },
                                    {
                                        "hidden": true,
                                        "name": "container",
                                        "required": false
                                    }
                                ],
                                "label": "set severity",
                                "name": "set_severity",
                                "refreshNotableData": true
                            }
                        },
                        "utilityType": "api",
                        "values": {
                            "set_severity": {
                                "_internal": [
                                    "container"
                                ],
                                "severity": "low"
                            }
                        }
                    },
                    "errors": {},
                    "id": "5",
                    "type": "utility",
                    "warnings": {},
                    "x": 800,
                    "y": 900
                },
                "6": {
                    "data": {
                        "advanced": {
                            "customName": "Set high severity",
                            "customNameId": 0,
                            "join": [],
                            "refreshNotableData": true
                        },
                        "functionId": 3,
                        "functionName": "set_high_severity",
                        "id": "6",
                        "loop": {
                            "enabled": false,
                            "exitAfterUnit": "m",
                            "exitAfterValue": 10,
                            "exitConditionEnabled": false,
                            "exitLoopAfter": 2,
                            "pauseUnit": "m",
                            "pauseValue": 2
                        },
                        "selectMore": false,
                        "tab": "apis",
                        "type": "utility",
                        "utilities": {
                            "set_severity": {
                                "description": "",
                                "fields": [
                                    {
                                        "choices": "notableSeverity",
                                        "description": "",
                                        "label": "severity",
                                        "name": "severity",
                                        "placeholder": "Select severity",
                                        "renderType": "dropdown",
                                        "required": true
                                    },
                                    {
                                        "hidden": true,
                                        "name": "container",
                                        "required": false
                                    }
                                ],
                                "label": "set severity",
                                "name": "set_severity",
                                "refreshNotableData": true
                            }
                        },
                        "utilityType": "api",
                        "values": {
                            "set_severity": {
                                "_internal": [
                                    "container"
                                ],
                                "severity": "high"
                            }
                        }
                    },
                    "errors": {},
                    "id": "6",
                    "type": "utility",
                    "userCode": "\n    # Write your custom code here...\n\n",
                    "warnings": {},
                    "x": 1420,
                    "y": 1240
                },
                "8": {
                    "data": {
                        "advanced": {
                            "join": []
                        },
                        "approver": {
                            "type": "role",
                            "value": "Administrator"
                        },
                        "functionId": 1,
                        "functionName": "prompt_1",
                        "id": "8",
                        "message": "The {0} incident with severity {1} has IP(s) outside of our list of countries.\n\n{2}",
                        "parameters": [
                            "container:name",
                            "container:severity",
                            "format_2:formatted_data"
                        ],
                        "responseTime": 1,
                        "responses": [
                            {
                                "required": true,
                                "responseOptions": [
                                    "Yes",
                                    "No"
                                ],
                                "responsePrompt": "Would you like to change severity to High?",
                                "responseType": "yes/no"
                            }
                        ],
                        "type": "prompt"
                    },
                    "errors": {},
                    "id": "8",
                    "type": "prompt",
                    "warnings": {},
                    "x": 1260,
                    "y": 900
                },
                "9": {
                    "data": {
                        "advanced": {
                            "case_sensitive": false,
                            "customName": "decide on prompt response",
                            "customNameId": 0,
                            "join": []
                        },
                        "conditions": [
                            {
                                "comparisons": [
                                    {
                                        "conditionIndex": 0,
                                        "op": "==",
                                        "param": "prompt_1:action_result.summary.responses.0",
                                        "value": "YES"
                                    }
                                ],
                                "conditionIndex": 0,
                                "conditionKey": "condition_key_0",
                                "customName": "said Yes totally eh",
                                "display": "If",
                                "logic": "and",
                                "type": "if"
                            }
                        ],
                        "functionId": 3,
                        "functionName": "decide_on_prompt_response",
                        "id": "9",
                        "type": "decision"
                    },
                    "errors": {},
                    "id": "9",
                    "type": "decision",
                    "warnings": {},
                    "x": 1340,
                    "y": 1060
                }
            },
            "notes": ""
        },
        "input_spec": null,
        "output_spec": null,
        "playbook_trigger": "artifact_created",
        "playbook_type": "automation",
        "python_version": "3.13",
        "schema": "5.0.22",
        "version": "7.0.0.198"
    },
    "create_time": "2026-04-24T17:11:33.255843+00:00",
    "draft_mode": false,
    "labels": [
        "*"
    ],
    "tags": []
}