{
    "blockly": false,
    "blockly_xml": "<xml></xml>",
    "category": "Uncategorized",
    "coa": {
        "data": {
            "clean": true,
            "code_block": "",
            "description": "",
            "hash": "e39c22d5d709bbe4ddc08b7028bc9bca5cdbcf79",
            "joint": {
                "cells": [
                    {
                        "0": "S",
                        "1": "T",
                        "2": "A",
                        "3": "R",
                        "4": "T",
                        "active": false,
                        "angle": 0,
                        "attrs": {
                            ".background": {
                                "fill": "#000000",
                                "stroke": "#5C6773"
                            },
                            ".color-band": {
                                "fill": "#3C444D"
                            },
                            ".outPorts>.port-out": {
                                "ref": ".background",
                                "ref-x": 0.5
                            },
                            ".outPorts>.port-out>.port-body": {
                                "port": {
                                    "id": "out",
                                    "type": "out"
                                }
                            },
                            ".title": {
                                "ref-x": 33,
                                "ref-y": 8,
                                "text": "START"
                            },
                            "g.delete": {
                                "display": "none"
                            },
                            "g.error": {
                                "opacity": 0
                            },
                            "g.icon image": {
                                "ref-x": 13,
                                "xlink:href": "/inc/coa/img/block_icon_start.svg"
                            },
                            "g.notes": {
                                "display": "block"
                            }
                        },
                        "block_code": "def on_start(container):\n    phantom.debug('on_start() called')\n    \n    # call 'whois_ip_1' block\n    whois_ip_1(container=container)\n\n    return",
                        "callback_code": "# read-only block view not available",
                        "callback_start": 1,
                        "callsback": false,
                        "connected_to_start": true,
                        "connection_name": "",
                        "connection_type": "",
                        "custom_callback": "",
                        "custom_code": "",
                        "custom_join": "",
                        "custom_name": "",
                        "description": "",
                        "has_custom": false,
                        "has_custom_block": false,
                        "has_custom_callback": false,
                        "has_custom_join": false,
                        "id": "7a5e6f42-2b08-4042-b97f-319879176314",
                        "inPorts": [],
                        "join_code": "# read-only block view not available",
                        "join_optional": [],
                        "join_start": 1,
                        "line_end": 16,
                        "line_start": 8,
                        "name": "",
                        "notes": "",
                        "number": 0,
                        "order": 1,
                        "outPorts": [
                            "out"
                        ],
                        "ports": {
                            "groups": {
                                "in": {
                                    "attrs": {
                                        ".port-body": {
                                            "fill": "#fff",
                                            "magnet": true,
                                            "r": 10,
                                            "stroke": "#000"
                                        },
                                        ".port-label": {
                                            "fill": "#000"
                                        }
                                    },
                                    "label": {
                                        "position": {
                                            "args": {
                                                "y": 10
                                            },
                                            "name": "left"
                                        }
                                    },
                                    "position": {
                                        "name": "left"
                                    }
                                },
                                "out": {
                                    "attrs": {
                                        ".port-body": {
                                            "fill": "#fff",
                                            "magnet": true,
                                            "r": 10,
                                            "stroke": "#000"
                                        },
                                        ".port-label": {
                                            "fill": "#000"
                                        }
                                    },
                                    "label": {
                                        "position": {
                                            "args": {
                                                "y": 10
                                            },
                                            "name": "right"
                                        }
                                    },
                                    "position": {
                                        "name": "right"
                                    }
                                }
                            }
                        },
                        "position": {
                            "x": 100,
                            "y": 100
                        },
                        "previous_function": "",
                        "previous_name": "",
                        "show_number": true,
                        "size": {
                            "height": 54,
                            "width": 80
                        },
                        "status": "",
                        "title": "START",
                        "type": "coa.StartEnd",
                        "warn": false,
                        "z": 1
                    },
                    {
                        "0": "E",
                        "1": "N",
                        "2": "D",
                        "active": false,
                        "angle": 0,
                        "attrs": {
                            ".background": {
                                "fill": "#000000",
                                "stroke": "#5C6773"
                            },
                            ".color-band": {
                                "fill": "#3C444D"
                            },
                            ".inPorts>.port-in": {
                                "ref": ".background",
                                "ref-x": 0.5
                            },
                            ".inPorts>.port-in>.port-body": {
                                "port": {
                                    "id": "in",
                                    "type": "in"
                                }
                            },
                            ".title": {
                                "text": "END"
                            },
                            "g.delete": {
                                "display": "none"
                            },
                            "g.error": {
                                "opacity": 0
                            },
                            "g.icon image": {
                                "xlink:href": "/inc/coa/img/block_icon_end.svg"
                            },
                            "g.notes": {
                                "display": "block"
                            }
                        },
                        "block_code": "def on_finish(container, summary):\n    phantom.debug('on_finish() called')\n    # This function is called after all actions are completed.\n    # summary of all the action and/or all detals of actions \n    # can be collected here.\n\n    # summary_json = phantom.get_summary()\n    # if 'result' in summary_json:\n        # for action_result in summary_json['result']:\n            # if 'action_run_id' in action_result:\n                # action_results = phantom.get_action_results(action_run_id=action_result['action_run_id'], result_data=False, flatten=False)\n                # phantom.debug(action_results)\n\n    return",
                        "callback_code": "# read-only block view not available",
                        "callback_start": 1,
                        "callsback": false,
                        "connected_to_start": true,
                        "connection_name": "whois ip",
                        "connection_type": "action",
                        "custom_callback": "",
                        "custom_code": "",
                        "custom_join": "",
                        "custom_name": "",
                        "description": "",
                        "has_custom": false,
                        "has_custom_block": false,
                        "has_custom_callback": false,
                        "has_custom_join": false,
                        "id": "85a2ae05-0676-4e22-b465-33adbcb38789",
                        "inPorts": [
                            "in"
                        ],
                        "join_code": "# read-only block view not available",
                        "join_optional": [],
                        "join_start": 1,
                        "line_end": 50,
                        "line_start": 37,
                        "name": "",
                        "notes": "",
                        "number": 0,
                        "order": 3,
                        "outPorts": [],
                        "ports": {
                            "groups": {
                                "in": {
                                    "attrs": {
                                        ".port-body": {
                                            "fill": "#fff",
                                            "magnet": true,
                                            "r": 10,
                                            "stroke": "#000"
                                        },
                                        ".port-label": {
                                            "fill": "#000"
                                        }
                                    },
                                    "label": {
                                        "position": {
                                            "args": {
                                                "y": 10
                                            },
                                            "name": "left"
                                        }
                                    },
                                    "position": {
                                        "name": "left"
                                    }
                                },
                                "out": {
                                    "attrs": {
                                        ".port-body": {
                                            "fill": "#fff",
                                            "magnet": true,
                                            "r": 10,
                                            "stroke": "#000"
                                        },
                                        ".port-label": {
                                            "fill": "#000"
                                        }
                                    },
                                    "label": {
                                        "position": {
                                            "args": {
                                                "y": 10
                                            },
                                            "name": "right"
                                        }
                                    },
                                    "position": {
                                        "name": "right"
                                    }
                                }
                            }
                        },
                        "position": {
                            "x": 820,
                            "y": 100
                        },
                        "previous_function": "",
                        "previous_name": "",
                        "show_number": true,
                        "size": {
                            "height": 54,
                            "width": 80
                        },
                        "status": "",
                        "title": "END",
                        "type": "coa.StartEnd",
                        "warn": false,
                        "z": 2
                    },
                    {
                        "attrs": {
                            ".connection": {
                                "stroke": "#6C7A89",
                                "stroke-width": 2
                            },
                            ".marker-target": {
                                "d": "M 10 0 L 0 5 L 10 10 z",
                                "fill": "#6a6c8a",
                                "stroke": "#6a6c8a"
                            }
                        },
                        "connector": {
                            "args": {
                                "radius": 5
                            },
                            "name": "rounded"
                        },
                        "endDirections": [
                            "left"
                        ],
                        "id": "88dd7fa1-1e8b-4526-abb6-fc0f8c89a7d8",
                        "router": {
                            "name": "metro"
                        },
                        "source": {
                            "id": "7a5e6f42-2b08-4042-b97f-319879176314",
                            "port": null,
                            "selector": "g:nth-child(1) > g:nth-child(2) > g:nth-child(1) > circle:nth-child(1)"
                        },
                        "startDirections": [
                            "right"
                        ],
                        "target": {
                            "id": "33c0b070-e21a-4c67-8b4c-9895abea47e1",
                            "selector": ".port-body[type=\"input\"]"
                        },
                        "type": "link",
                        "z": 3
                    },
                    {
                        "action": "whois ip",
                        "action_type": "investigate",
                        "active": false,
                        "active_keys": {},
                        "active_values": {
                            "ip": "artifact:*.cef.sourceAddress"
                        },
                        "angle": 0,
                        "app": "WHOIS",
                        "appid": "e6723c2e-06ef-415a-8098-62c46c1cb71f",
                        "approver": "",
                        "assets": [
                            {
                                "action": "whois ip",
                                "actions": [
                                    "whois ip",
                                    "whois domain"
                                ],
                                "active": true,
                                "app_name": "WHOIS",
                                "app_version": "1.2.31",
                                "appid": "e6723c2e-06ef-415a-8098-62c46c1cb71f",
                                "asset_name": "whois",
                                "config_type": "asset",
                                "count": 0,
                                "fields": {
                                    "ip": "artifact:*.cef.sourceAddress"
                                },
                                "has_app": true,
                                "id": 3,
                                "loaded": false,
                                "missing": false,
                                "name": "whois",
                                "output": [
                                    {
                                        "contains": [
                                            "ip"
                                        ],
                                        "data_path": "action_result.parameter.ip",
                                        "data_type": "string"
                                    },
                                    {
                                        "column_name": "Asn",
                                        "column_order": 2,
                                        "data_path": "action_result.data.*.asn",
                                        "data_type": "string"
                                    },
                                    {
                                        "column_name": "Asn Cidr",
                                        "column_order": 3,
                                        "data_path": "action_result.data.*.asn_cidr",
                                        "data_type": "string"
                                    },
                                    {
                                        "column_name": "Asn Country Code",
                                        "column_order": 4,
                                        "data_path": "action_result.data.*.asn_country_code",
                                        "data_type": "string"
                                    },
                                    {
                                        "column_name": "Asn Date",
                                        "column_order": 5,
                                        "data_path": "action_result.data.*.asn_date",
                                        "data_type": "string"
                                    },
                                    {
                                        "column_name": "Asn Registry",
                                        "column_order": 6,
                                        "data_path": "action_result.data.*.asn_registry",
                                        "data_type": "string"
                                    },
                                    {
                                        "column_name": "Abuse Emails",
                                        "column_order": 7,
                                        "contains": [
                                            "email"
                                        ],
                                        "data_path": "action_result.data.*.nets.*.abuse_emails",
                                        "data_type": "string"
                                    },
                                    {
                                        "column_name": "Address",
                                        "column_order": 8,
                                        "data_path": "action_result.data.*.nets.*.address",
                                        "data_type": "string"
                                    },
                                    {
                                        "column_name": "Cidr",
                                        "column_order": 9,
                                        "data_path": "action_result.data.*.nets.*.cidr",
                                        "data_type": "string"
                                    },
                                    {
                                        "column_name": "City",
                                        "column_order": 10,
                                        "data_path": "action_result.data.*.nets.*.city",
                                        "data_type": "string"
                                    },
                                    {
                                        "column_name": "Country",
                                        "column_order": 11,
                                        "data_path": "action_result.data.*.nets.*.country",
                                        "data_type": "string"
                                    },
                                    {
                                        "column_name": "Created",
                                        "column_order": 12,
                                        "data_path": "action_result.data.*.nets.*.created",
                                        "data_type": "string"
                                    },
                                    {
                                        "column_name": "Description",
                                        "column_order": 13,
                                        "data_path": "action_result.data.*.nets.*.description",
                                        "data_type": "string"
                                    },
                                    {
                                        "column_order": 7,
                                        "contains": [
                                            "email"
                                        ],
                                        "data_path": "action_result.data.*.nets.*.emails",
                                        "data_type": "string"
                                    },
                                    {
                                        "data_path": "action_result.data.*.nets.*.handle",
                                        "data_type": "string"
                                    },
                                    {
                                        "column_name": "Name",
                                        "column_order": 14,
                                        "data_path": "action_result.data.*.nets.*.name",
                                        "data_type": "string"
                                    },
                                    {
                                        "column_name": "Postal Code",
                                        "column_order": 15,
                                        "data_path": "action_result.data.*.nets.*.postal_code",
                                        "data_type": "string"
                                    },
                                    {
                                        "column_name": "Range",
                                        "column_order": 16,
                                        "data_path": "action_result.data.*.nets.*.range",
                                        "data_type": "string"
                                    },
                                    {
                                        "column_name": "State",
                                        "column_order": 17,
                                        "data_path": "action_result.data.*.nets.*.state",
                                        "data_type": "string"
                                    },
                                    {
                                        "column_name": "Tech Emails",
                                        "column_order": 18,
                                        "contains": [
                                            "email"
                                        ],
                                        "data_path": "action_result.data.*.nets.*.tech_emails",
                                        "data_type": "string"
                                    },
                                    {
                                        "column_name": "Updated",
                                        "column_order": 19,
                                        "data_path": "action_result.data.*.nets.*.updated",
                                        "data_type": "string"
                                    },
                                    {
                                        "data_path": "action_result.data.*.query",
                                        "data_type": "string"
                                    },
                                    {
                                        "column_name": "IP",
                                        "column_order": 0,
                                        "contains": [
                                            "ip"
                                        ],
                                        "data_path": "action_result.parameter.ip",
                                        "data_type": "string"
                                    },
                                    {
                                        "column_name": "Misc Emails",
                                        "column_order": 20,
                                        "contains": [
                                            "email"
                                        ],
                                        "data_path": "action_result.data.*.nets.*.misc_emails",
                                        "data_type": "string"
                                    },
                                    {
                                        "data_path": "action_result.summary.asn",
                                        "data_type": "string"
                                    },
                                    {
                                        "data_path": "action_result.summary.country_code",
                                        "data_type": "string"
                                    },
                                    {
                                        "data_path": "action_result.summary.nets.*.address",
                                        "data_type": "string"
                                    },
                                    {
                                        "data_path": "action_result.summary.nets.*.range",
                                        "data_type": "string"
                                    },
                                    {
                                        "data_path": "action_result.summary.registry",
                                        "data_type": "string"
                                    },
                                    {
                                        "data_path": "summary.total_objects",
                                        "data_type": "numeric"
                                    },
                                    {
                                        "data_path": "action_result.status",
                                        "data_type": "string"
                                    },
                                    {
                                        "data_path": "action_result.message",
                                        "data_type": "string"
                                    },
                                    {
                                        "data_path": "summary.total_objects_successful",
                                        "data_type": "numeric"
                                    }
                                ],
                                "parameters": {
                                    "ip": {
                                        "contains": [
                                            "ip"
                                        ],
                                        "data_type": "string",
                                        "default": null,
                                        "description": "IP to query",
                                        "key": "ip",
                                        "order": 0,
                                        "primary": true,
                                        "required": true
                                    }
                                },
                                "product_name": "Whois",
                                "product_vendor": "Generic",
                                "targets": "3",
                                "type": "information"
                            }
                        ],
                        "attrs": {
                            ".action": {
                                "text": "whois ip"
                            },
                            ".background": {
                                "fill": "#000000",
                                "stroke": "#5C6773"
                            },
                            ".color-band": {
                                "fill": "#3C444D"
                            },
                            ".inPorts>.port-in": {
                                "ref": ".background",
                                "ref-x": 0.5
                            },
                            ".inPorts>.port-in>.port-body": {
                                "port": {
                                    "id": "in",
                                    "type": "in"
                                }
                            },
                            ".message": {
                                "opacity": 0,
                                "ref-x": 5,
                                "ref-y": 105,
                                "text": "Configuring now"
                            },
                            ".outPorts>.port-out": {
                                "ref": ".background",
                                "ref-x": 0.5
                            },
                            ".outPorts>.port-out>.port-body": {
                                "port": {
                                    "id": "out",
                                    "type": "out"
                                }
                            },
                            ".title": {
                                "text": "Investigate"
                            },
                            "g.delete": {
                                "display": "none"
                            },
                            "g.error": {
                                "opacity": 0
                            },
                            "g.icon image": {
                                "xlink:href": "/inc/coa/img/block_icon_investigate.svg"
                            },
                            "g.notes": {
                                "display": "block"
                            }
                        },
                        "block_code": "def whois_ip_1(action=None, success=None, container=None, results=None, handle=None, filtered_artifacts=None, filtered_results=None):\n    phantom.debug('whois_ip_1() called')\n\n    # collect data for 'whois_ip_1' call\n    container_data = phantom.collect2(container=container, datapath=['artifact:*.cef.sourceAddress', 'artifact:*.id'])\n\n    parameters = []\n    \n    # build parameters list for 'whois_ip_1' call\n    for container_item in container_data:\n        if container_item[0]:\n            parameters.append({\n                'ip': container_item[0],\n                # context (artifact id) is added to associate results with the artifact\n                'context': {'artifact_id': container_item[1]},\n            })\n\n    phantom.act(\"whois ip\", parameters=parameters, assets=['whois'], name=\"whois_ip_1\")\n\n    return",
                        "callback_code": "",
                        "callback_start": 1,
                        "callsback": true,
                        "color": "",
                        "connected_to_start": true,
                        "connection_name": "",
                        "connection_type": "",
                        "custom_callback": "",
                        "custom_code": "",
                        "custom_join": "",
                        "custom_name": "",
                        "delay": 0,
                        "description": "",
                        "has_custom": false,
                        "has_custom_block": false,
                        "has_custom_callback": false,
                        "has_custom_join": false,
                        "id": "33c0b070-e21a-4c67-8b4c-9895abea47e1",
                        "inPorts": [
                            "in"
                        ],
                        "join_code": "",
                        "join_optional": [],
                        "join_start": 1,
                        "line_end": 37,
                        "line_start": 16,
                        "message": "Configuring now",
                        "name": "whois ip",
                        "notes": "",
                        "number": 1,
                        "order": 2,
                        "outPorts": [
                            "out"
                        ],
                        "ports": {
                            "groups": {
                                "in": {
                                    "attrs": {
                                        ".port-body": {
                                            "fill": "#fff",
                                            "magnet": true,
                                            "r": 10,
                                            "stroke": "#000"
                                        },
                                        ".port-label": {
                                            "fill": "#000"
                                        }
                                    },
                                    "label": {
                                        "position": {
                                            "args": {
                                                "y": 10
                                            },
                                            "name": "left"
                                        }
                                    },
                                    "position": {
                                        "name": "left"
                                    }
                                },
                                "out": {
                                    "attrs": {
                                        ".port-body": {
                                            "fill": "#fff",
                                            "magnet": true,
                                            "r": 10,
                                            "stroke": "#000"
                                        },
                                        ".port-label": {
                                            "fill": "#000"
                                        }
                                    },
                                    "label": {
                                        "position": {
                                            "args": {
                                                "y": 10
                                            },
                                            "name": "right"
                                        }
                                    },
                                    "position": {
                                        "name": "right"
                                    }
                                }
                            }
                        },
                        "position": {
                            "x": 320,
                            "y": 80
                        },
                        "previous_function": "",
                        "previous_name": "whois_ip_1",
                        "required_params": {
                            "ip": true
                        },
                        "reviewer": "",
                        "show_number": false,
                        "size": {
                            "height": 100,
                            "width": 180
                        },
                        "state": "app_action_assets",
                        "status": "",
                        "title": "Investigate",
                        "type": "coa.Action",
                        "warn": "",
                        "z": 5
                    },
                    {
                        "attrs": {
                            ".connection": {
                                "stroke": "#6C7A89",
                                "stroke-width": 2
                            },
                            ".marker-target": {
                                "d": "M 10 0 L 0 5 L 10 10 z",
                                "fill": "#6a6c8a",
                                "stroke": "#6a6c8a"
                            }
                        },
                        "connector": {
                            "args": {
                                "radius": 5
                            },
                            "name": "rounded"
                        },
                        "endDirections": [
                            "left"
                        ],
                        "id": "16faf9f5-1365-4970-9564-43f39dbc2eb8",
                        "router": {
                            "name": "metro"
                        },
                        "source": {
                            "id": "33c0b070-e21a-4c67-8b4c-9895abea47e1",
                            "port": null,
                            "selector": "g:nth-child(1) > g:nth-child(2) > g:nth-child(1) > circle:nth-child(1)"
                        },
                        "startDirections": [
                            "right"
                        ],
                        "target": {
                            "id": "85a2ae05-0676-4e22-b465-33adbcb38789",
                            "port": null,
                            "selector": "g:nth-child(1) > g:nth-child(1) > g:nth-child(1) > circle:nth-child(1)"
                        },
                        "type": "link",
                        "z": 6
                    }
                ]
            },
            "notes": ""
        },
        "schema": 3,
        "version": "4.1.94"
    },
    "create_time": "2019-06-25T17:56:47.239971+00:00",
    "draft_mode": false,
    "labels": [
        "*"
    ]
}